llm_onesdk/__init__.py
llm_onesdk/core.py
llm_onesdk/models/__init__.py
llm_onesdk/models/base_api.py
llm_onesdk/models/anthropic/__init__.py
llm_onesdk/models/anthropic/api.py
llm_onesdk/models/baichuan/__init__.py
llm_onesdk/models/baichuan/api.py
llm_onesdk/models/cohere/__init__.py
llm_onesdk/models/cohere/api.py
llm_onesdk/models/doubao/__init__.py
llm_onesdk/models/doubao/api.py
llm_onesdk/models/gemini/__init__.py
llm_onesdk/models/gemini/api.py
llm_onesdk/models/kimi/__init__.py
llm_onesdk/models/kimi/api.py
llm_onesdk/models/minimax/__init__.py
llm_onesdk/models/minimax/api.py
llm_onesdk/models/ollama/__init__.py
llm_onesdk/models/ollama/api.py
llm_onesdk/models/openai/__init__.py
llm_onesdk/models/openai/api.py
llm_onesdk/models/qwen/__init__.py
llm_onesdk/models/qwen/api.py
llm_onesdk/models/wenxin/__init__.py
llm_onesdk/models/wenxin/api.py
llm_onesdk/utils/__init__.py
llm_onesdk/utils/config.py
llm_onesdk/utils/error_handler.py
llm_onesdk/utils/logger.py
test/__init__.py
test/test_anthropic_api.py
test/test_baichuan_api.py
test/test_doubao_api.py
test/test_kimi_api.py
test/test_minimax_api.py
test/test_openai_api.py
test/test_qwen_api.py
test/test_wenxin_api.py
llm_onesdk-0.0.7.dist-info/LICENSE
llm_onesdk-0.0.7.dist-info/METADATA
llm_onesdk-0.0.7.dist-info/WHEEL
llm_onesdk-0.0.7.dist-info/top_level.txt
llm_onesdk-0.0.7.dist-info/RECORD
