Metadata-Version: 2.1
Name: llm_onesdk
Version: 0.0.7
Summary: OneSDK is a Python library that provides a unified interface for interacting with various Large Language Model (LLM) providers.
Home-page: https://onesdk.llmpages.cn/
Author: anycodes
Author-email: liuyu@xmail.tech
License: MIT
Project-URL: GitHub, https://github.com/LLMPages/onesdk
Keywords: LLM API SDK NLP AI
Classifier: Programming Language :: Python :: 3
Classifier: License :: OSI Approved :: MIT License
Classifier: Operating System :: OS Independent
Requires-Python: >=3.7
License-File: LICENSE
Requires-Dist: requests<3,>=2.25.1
Requires-Dist: python-dotenv<1,>=0.19.0
Requires-Dist: typing-extensions<5,>=3.7.4
Provides-Extra: test
Requires-Dist: unittest2>=1.1.0; extra == "test"
